stmd/__init__.py
stmd/__main__.py
stmd/options.py
stmd-0.0.2.dist-info/METADATA
stmd-0.0.2.dist-info/WHEEL
stmd-0.0.2.dist-info/entry_points.txt
stmd-0.0.2.dist-info/top_level.txt
stmd-0.0.2.dist-info/RECORD
