Metadata-Version: 2.1
Name: stmd
Version: 0.0.2
Summary: stmd - Scrape to Markdown
License: GNU General Public License v3 (GPLv3)
Project-URL: repository, https://codeberg.org/johndovern/stmd
Requires-Dist: requests
Requires-Dist: BeautifulSoup4
Requires-Dist: html2text
